automa/bot/__init__.py
automa/bot/webhook.py
automa_bot_sdk-0.0.2.dist-info/METADATA
automa_bot_sdk-0.0.2.dist-info/WHEEL
automa_bot_sdk-0.0.2.dist-info/top_level.txt
automa_bot_sdk-0.0.2.dist-info/RECORD
