Metadata-Version: 2.4
Name: automa-bot-sdk
Version: 0.0.2
Summary: Bot helpers for Automa
Author-email: "Automa, Inc." <engineering@automa.app>
License-Expression: MIT
Project-URL: Homepage, https://automa.app
Project-URL: Repository, https://github.com/automa/sdk-python
Requires-Python: >=3.11
